{
    "IgxComboClearIconDirective": {
        "comment": {
            "tags": {
                "igxmodule": {
                    "comment": {
                        "text": "IgxComboModule",
                        "tagName": "igxmodule"
                    }
                },
                "igxtheme": {
                    "comment": {
                        "text": "igx-combo-theme",
                        "tagName": "igxtheme"
                    }
                },
                "igxkeywords": {
                    "comment": {
                        "text": "コンボボックス、コンボ選択",
                        "tagName": "igxkeywords"
                    }
                },
                "igxgroup": {
                    "comment": {
                        "text": "グリッドとリスト",
                        "tagName": "igxgroup"
                    }
                },
                "example": {
                    "comment": {
                        "text": [
                            " <igx-combo #combo>",
                            "     <ng-template igxComboClearIcon>",
                            "         <igx-icon>clear</igx-icon>",
                            "     </ng-template>",
                            " </igx-combo>"
                        ],
                        "tagName": "例:"
                    }
                }
            },
            "shortText": "コンボのクリア アイコンを描画するときに使用されるカスタム テンプレートを定義します。"
        },
        "properties": {},
        "methods": {},
        "accessors": {}
    }
}