{
    "IgxComboEmptyDirective": {
        "comment": {
            "tags": {
                "igxmodule": {
                    "comment": {
                        "text": "IgxComboModule",
                        "tagName": "igxmodule"
                    }
                },
                "igxtheme": {
                    "comment": {
                        "text": "igx-combo-theme",
                        "tagName": "igxtheme"
                    }
                },
                "igxkeywords": {
                    "comment": {
                        "text": "コンボボックス、コンボ選択",
                        "tagName": "igxkeywords"
                    }
                },
                "igxgroup": {
                    "comment": {
                        "text": "グリッドとリスト",
                        "tagName": "igxgroup"
                    }
                },
                "example": {
                    "comment": {
                        "text": [
                            " <igx-combo>",
                            "     <ng-template igxComboEmpty>",
                            "         <div class=\"combo--empty\">",
                            "             表示する項目はありません。",
                            "         </div>",
                            "     </ng-template>",
                            " </igx-combo>"
                        ],
                        "tagName": "例:"
                    }
                }
            },
            "shortText": "コンボのリストが空のときに表示されるカスタム テンプレートを定義します。"
        },
        "properties": {},
        "methods": {},
        "accessors": {}
    }
}