{
    "IScrollStrategy": {
        "comment": {
            "tags": {},
            "shortText": [
                "[Documentation](https://www.infragistics.com/products/ignite-ui-angular/angular/components/overlay-scroll).",
                "Scroll strategies determines how the scrolling will be handled in the provided IgxOverlayService."
            ]
        },
        "properties": {},
        "methods": {
            "initialize": {
                "comment": {
                    "parameters": {
                        "document": {
                            "comment": {
                                "shortText": "reference to Document object."
                            }
                        },
                        "overlayService": {
                            "comment": {
                                "shortText": "IgxOverlay service to use in this strategy."
                            }
                        },
                        "id": {
                            "comment": {
                                "shortText": [
                                    "Unique id for this strategy.",
                                    "```typescript",
                                    "settings.scrollStrategy.initialize(document, overlay, id);",
                                    "```"
                                ]
                            }
                        }
                    },
                    "tags": {},
                    "shortText": "Initializes the strategy. Should be called once"
                }
            },
            "attach": {
                "comment": {
                    "tags": {},
                    "shortText": [
                        "Attaches the strategy",
                        "```typescript",
                        "settings.scrollStrategy.attach();",
                        "```"
                    ]
                }
            },
            "detach": {
                "comment": {
                    "tags": {},
                    "shortText": [
                        "Detaches the strategy",
                        "```typescript",
                        "settings.scrollStrategy.detach();",
                        "```"
                    ]
                }
            }
        }
    }
}