{
    "ContainerPositionStrategy": {
        "comment": {
            "tags": {},
            "shortText": [
                "Positions the element inside the containing outlet based on the directions passed in trough PositionSettings.",
                "These are Top/Middle/Bottom for verticalDirection and Left/Center/Right for horizontalDirection"
            ]
        },
        "properties": {
            "settings": {
                "comment": {
                    "tags": {},
                    "shortText": "PositionSettings to use when position the component in the overlay"
                }
            }
        },
        "methods": {
            "position": {
                "comment": {
                    "tags": {
                        "inheritdoc": {
                            "comment": {
                                "tagName": "inheritdoc"
                            }
                        }
                    }
                }
            },
            "clone": {
                "comment": {
                    "tags": {
                        "inheritdoc": {
                            "comment": {
                                "tagName": "inheritdoc"
                            }
                        }
                    }
                }
            }
        },
        "accessors": {}
    }
}