{
    "IgxQueryBuilderComponent": {
        "comment": {
            "blockTags": [
                {
                    "tag": "@例",
                    "content": [
                        {
                            "kind": "code",
                            "text": "```html\n<igx-query-builder [fields]=\"this.fields\">\n</igx-query-builder>\n```"
                        }
                    ]
                }
            ],
            "modifierTags": {},
            "summary": [
                {
                    "kind": "text",
                    "text": "条件を作成または編集し、AND/OR ロジックを使用してグループ化することにより、複雑なフィルターを操作するために使用されるコンポーネント。\nグリッドの高度なフィルタリングで内部的に使用されます。"
                }
            ]
        },
        "properties": {
            "expressionTreeChange": {
                "comment": {
                    "blockTags": [],
                    "modifierTags": {},
                    "summary": [
                        {
                            "kind": "text",
                            "text": "式ツリーが変更されたときに発生するイベント。\n\n"
                        },
                        {
                            "kind": "code",
                            "text": "```html\n <igx-query-builder (expressionTreeChange)='onExpressionTreeChange()'></igx-query-builder>\n```"
                        }
                    ]
                }
            }
        },
        "methods": {
            "getComponentSizeStyles": {
                "comment": {
                    "blockTags": [],
                    "modifierTags": {},
                    "summary": [
                        {
                            "kind": "text",
                            "text": "表示密度の値に基づいて "
                        },
                        {
                            "kind": "code",
                            "text": "`--component-size`"
                        },
                        {
                            "kind": "text",
                            "text": " CSS 変数を設定します。"
                        }
                    ]
                }
            }
        },
        "accessors": {
            "fields": {
                "getter": {
                    "comment": {
                        "blockTags": [],
                        "modifierTags": {},
                        "summary": [
                            {
                                "kind": "text",
                                "text": "フィールドを返します。"
                            }
                        ]
                    }
                },
                "setter": {
                    "comment": {
                        "blockTags": [
                            {
                                "tag": "@Input",
                                "content": [
                                    {
                                        "kind": "text",
                                        "text": "フィールドを設定する @Input プロパティ。"
                                    }
                                ]
                            }
                        ],
                        "modifierTags": {},
                        "summary": [
                            {
                                "kind": "text",
                                "text": "\n"
                            }
                        ]
                    }
                }
            },
            "expressionTree": {
                "getter": {
                    "comment": {
                        "blockTags": [],
                        "modifierTags": {},
                        "summary": [
                            {
                                "kind": "text",
                                "text": "式ツリーを返します。"
                            }
                        ]
                    }
                },
                "setter": {
                    "comment": {
                        "blockTags": [
                            {
                                "tag": "@Input",
                                "content": [
                                    {
                                        "kind": "text",
                                        "text": "式ツリーを設定する @Input プロパティ。"
                                    }
                                ]
                            }
                        ],
                        "modifierTags": {},
                        "summary": [
                            {
                                "kind": "text",
                                "text": "\n"
                            }
                        ]
                    }
                }
            },
            "locale": {
                "getter": {
                    "comment": {
                        "blockTags": [],
                        "modifierTags": {},
                        "summary": [
                            {
                                "kind": "text",
                                "text": "クエリ ビルダーの "
                            },
                            {
                                "kind": "code",
                                "text": "`locale`"
                            },
                            {
                                "kind": "text",
                                "text": " を取得します。\n設定されていない場合、デフォルトでアプリケーションのロケールになります。"
                            }
                        ]
                    }
                },
                "setter": {
                    "comment": {
                        "blockTags": [],
                        "modifierTags": {},
                        "summary": [
                            {
                                "kind": "text",
                                "text": "クエリ ビルダーの "
                            },
                            {
                                "kind": "code",
                                "text": "`locale`"
                            },
                            {
                                "kind": "text",
                                "text": " を設定します。\n有効な BCP 47 言語タグに設定します。"
                            }
                        ]
                    }
                }
            },
            "resourceStrings": {
                "getter": {
                    "comment": {
                        "blockTags": [],
                        "modifierTags": {},
                        "summary": [
                            {
                                "kind": "text",
                                "text": "リソース文字列を返します。"
                            }
                        ]
                    }
                },
                "setter": {
                    "comment": {
                        "blockTags": [],
                        "modifierTags": {},
                        "summary": [
                            {
                                "kind": "text",
                                "text": "リソース文字列を設定します。\nデフォルトで EN リソースを使用します。"
                            }
                        ]
                    }
                }
            },
            "displayDensity": {
                "getter": {
                    "comment": {
                        "blockTags": [
                            {
                                "tag": "@非推奨",
                                "content": [
                                    {
                                        "kind": "text",
                                        "text": "バージョン 16.1.x 以降。\n"
                                    },
                                    {
                                        "kind": "code",
                                        "text": "`--ig-size`"
                                    },
                                    {
                                        "kind": "text",
                                        "text": " CSS カスタム プロパティを使用してください。"
                                    }
                                ]
                            },
                            {
                                "tag": "@参照",
                                "content": [
                                    {
                                        "kind": "inline-tag",
                                        "tag": "@link",
                                        "text": "[アップデート ガイド](https://jp.infragistics.com/products/ignite-ui-angular/angular/components/general/update-guide#160x-から-161x-の場合)"
                                    },
                                    {
                                        "kind": "text",
                                        "text": "\n\nコンポーネントのテーマを返します。\nデフォルトのテーマは "
                                    },
                                    {
                                        "kind": "code",
                                        "text": "`comfortable`"
                                    },
                                    {
                                        "kind": "text",
                                        "text": " です。\n利用可能なオプションは "
                                    },
                                    {
                                        "kind": "code",
                                        "text": "`comfortable`"
                                    },
                                    {
                                        "kind": "text",
                                        "text": "、"
                                    },
                                    {
                                        "kind": "code",
                                        "text": "`cosy`"
                                    },
                                    {
                                        "kind": "text",
                                        "text": "、または "
                                    },
                                    {
                                        "kind": "code",
                                        "text": "`compact`"
                                    },
                                    {
                                        "kind": "text",
                                        "text": " です。\n"
                                    },
                                    {
                                        "kind": "code",
                                        "text": "```typescript\nlet componentTheme = this.component.displayDensity;\n```"
                                    }
                                ]
                            }
                        ],
                        "modifierTags": {},
                        "summary": []
                    }
                },
                "setter": {
                    "comment": {
                        "blockTags": [],
                        "modifierTags": {},
                        "summary": [
                            {
                                "kind": "text",
                                "text": "コンポーネントのテーマを設定します。"
                            }
                        ]
                    }
                }
            }
        }
    }
}