{
    "action-strip": {
        "parameters": {
            "theme": {
                "description": [
                    "コンポーネントのスタイル設定に使用されるテーマ。"
                ]
            }
        }
    },
    "date-picker": {
        "parameters": {
            "theme": {
                "description": [
                    "コンポーネントのスタイル設定に使用されるカレンダー テーマ。"
                ]
            }
        }
    },
    "excel-filtering": {
        "parameters": {
            "theme": {
                "description": [
                    "コンポーネントのスタイル設定に使用されるグリッド テーマ。"
                ]
            }
        }
    },
    "pivot-data-selector": {
        "parameters": {
            "theme": {
                "description": [
                    "コンポーネントのスタイル設定に使用されるテーマ。"
                ]
            }
        }
    },
    "file-input": {
        "parameters": {
            "theme": {
                "description": [
                    "コンポーネントのスタイル設定に使用されるテーマ。"
                ]
            }
        }
    },
    "query-builder": {
        "parameters": {
            "theme": {
                "description": [
                    "コンポーネントのスタイル設定に使用されるグリッド テーマ。"
                ]
            }
        }
    },
    "core": {
        "parameters": {
            "print-layout": {
                "description": [
                    "コンポーネントの印刷スタイルをアクティブにします。"
                ]
            },
            "enhanced-accesibility": {
                "description": [
                    "コンポーネントの色およびその他のプロパティをアクセスしやすい値に切り替えます。"
                ]
            }
        }
    },
    "css-vars": {
        "description": [
            "テーマの色を CSS 変数として特定のスコープに追加します。",
            ""
        ],
        "parameters": {
            "theme": {
                "description": [
                    "使用するコンポーネントのテーマ。"
                ]
            },
            "scope": {
                "description": [
                    "使用する CSS 変数のスコープ。(オプション)"
                ]
            }
        },
        "example": [
            {
                "description": [
                    "グリッド テーマの色を CSS 変数に変換します。"
                ],
                "code": [
                    "$my-grid-theme grid-theme(",
                    "  $header-background: red,",
                    "  $content-background: #222",
                    ");",
                    ".my-grid {",
                    "  @include css-vars($my-grid-theme);",
                    "}"
                ]
            }
        ]
    },
    "sizable": {
        "description": [
            "スコープがサイズの変更に対応できるように、必要な CSS プロパティを追加します。",
            ""
        ],
        "example": [
            {
                "description": [
                    "例"
                ],
                "code": [
                    ".my-component {",
                    "  @include sizable();",
                    "}"
                ]
            }
        ]
    },
    "theme": {
        "description": [
            "Ignite UI for Angular のグローバル テーマを生成します。",
            ""
        ],
        "parameters": {
            "palette": {
                "description": [
                    "グローバル テーマで使用されるパレット。"
                ]
            },
            "schema": {
                "description": [
                    "コンポーネントのスタイル設定に基づいて使用されるスキーマ。"
                ]
            },
            "exclude": {
                "description": [
                    "グローバル テーマのスタイルから除外される igx コンポーネントのリスト。"
                ]
            },
            "roundness": {
                "description": [
                    "すべてのコンポーネントのグローバルな丸み係数 (値は 0〜1 の任意の小数にすることができます) を設定します。"
                ]
            },
            "elevation": {
                "description": [
                    "テーマのすべてのコンポーネントのエレベーションのオン/オフを切り替えます。"
                ]
            },
            "elevations": {
                "description": [
                    "すべてのコンポーネント テーマで使用されるエレベーション マップ。"
                ]
            }
        }
    },
    "theme-internal": {
        "description": [
            "Ignite UI for Angular のグローバル テーマを生成します。",
            ""
        ],
        "parameters": {
            "palette": {
                "description": [
                    "グローバル テーマで使用されるパレット。"
                ]
            },
            "schema": {
                "description": [
                    "コンポーネントのスタイル設定に基づいて使用されるスキーマ。"
                ]
            },
            "exclude": {
                "description": [
                    "グローバル テーマのスタイルから除外される igx コンポーネントのリスト。"
                ]
            },
            "roundness": {
                "description": [
                    "すべてのコンポーネントのグローバルな丸み係数 (値は 0〜1 の任意の小数にすることができます) を設定します。"
                ]
            },
            "elevation": {
                "description": [
                    "テーマのすべてのコンポーネントのエレベーションのオン/オフを切り替えます。"
                ]
            },
            "elevations": {
                "description": [
                    "すべてのコンポーネント テーマで使用されるエレベーション マップ。"
                ]
            }
        }
    },
    "light-theme": {
        "description": [
            "テーマ ミックスインのラッパー。ライト背景で使用できるグローバルなマテリアル テーマを作成します。",
            ""
        ],
        "parameters": {
            "palette": {
                "description": [
                    "グローバル テーマで使用されるパレット。"
                ]
            },
            "exclude": {
                "description": [
                    "グローバル テーマのスタイルから除外される ig コンポーネントのリスト。"
                ]
            }
        }
    },
    "dark-theme": {
        "description": [
            "テーマ ミックスインのラッパー。ダーク背景で使用できるグローバルなマテリアル テーマを作成します。",
            ""
        ],
        "parameters": {
            "palette": {
                "description": [
                    "グローバル テーマで使用されるパレット。"
                ]
            },
            "exclude": {
                "description": [
                    "グローバル テーマのスタイルから除外される igx コンポーネントのリスト。"
                ]
            }
        }
    },
    "bootstrap-light-theme": {
        "description": [
            "テーマ ミックスインのラッパー。ライト背景で使用されるグローバル bootstrap のようなテーマを作成します。",
            ""
        ],
        "parameters": {
            "palette": {
                "description": [
                    "グローバル テーマで使用されるパレット。"
                ]
            },
            "exclude": {
                "description": [
                    "グローバル テーマのスタイルから除外される ig コンポーネントのリスト。"
                ]
            }
        }
    },
    "bootstrap-dark-theme": {
        "description": [
            "テーマ ミックスインのラッパー。ダーク背景で使用されるグローバル bootstrap のようなテーマを作成します。",
            ""
        ],
        "parameters": {
            "palette": {
                "description": [
                    "グローバル テーマで使用されるパレット。"
                ]
            },
            "exclude": {
                "description": [
                    "グローバル テーマのスタイルから除外される ig コンポーネントのリスト。"
                ]
            }
        }
    },
    "fluent-light-theme": {
        "description": [
            "テーマ ミックスインのラッパー。ライト背景で使用されるグローバル fluent テーマを作成します。",
            ""
        ],
        "parameters": {
            "palette": {
                "description": [
                    "グローバル テーマで使用されるパレット。"
                ]
            },
            "exclude": {
                "description": [
                    "グローバル テーマのスタイルから除外される ig コンポーネントのリスト。"
                ]
            }
        }
    },
    "fluent-dark-theme": {
        "description": [
            "テーマ ミックスインのラッパー。ダーク背景で使用されるグローバル fluent テーマを作成します。",
            ""
        ],
        "parameters": {
            "palette": {
                "description": [
                    "グローバル テーマで使用されるパレット。"
                ]
            },
            "exclude": {
                "description": [
                    "グローバル テーマのスタイルから除外される ig コンポーネントのリスト。"
                ]
            }
        }
    },
    "indigo-light-theme": {
        "description": [
            "テーマ ミックスインのラッパー。ライト背景で使用できるグローバルなインディゴ テーマを作成します。",
            ""
        ],
        "parameters": {
            "palette": {
                "description": [
                    "グローバル テーマで使用されるパレット。"
                ]
            },
            "exclude": {
                "description": [
                    "グローバル テーマのスタイルから除外される ig コンポーネントのリスト。"
                ]
            }
        }
    },
    "indigo-dark-theme": {
        "description": [
            "テーマ ミックスインのラッパー。ダーク背景で使用できるグローバル インディゴ テーマを作成します。",
            ""
        ],
        "parameters": {
            "palette": {
                "description": [
                    "グローバル テーマで使用されるパレット。"
                ]
            },
            "exclude": {
                "description": [
                    "グローバル テーマのスタイルから除外される ig コンポーネントのリスト。"
                ]
            }
        }
    }
}