{
    "IPivotKeys": {
        "comment": {
            "tags": {},
            "shortText": [
                "データ生成に使用されるピボット データ キーを説明するインターフェイス。",
                "データが事前に入力されているカスタム リモート シナリオに使用できます。"
            ]
        },
        "properties": {
            "children": {
                "comment": {
                    "tags": {},
                    "shortText": "階層構築の子を保存するフィールド。"
                }
            },
            "records": {
                "comment": {
                    "tags": {},
                    "shortText": "元のデータ レコードへの参照を格納するフィールド。"
                }
            },
            "aggregations": {
                "comment": {
                    "tags": {},
                    "shortText": "集計値を格納するフィールド。"
                }
            },
            "level": {
                "comment": {
                    "tags": {},
                    "shortText": "階層に基づいてディメンション レベルを格納するフィールド。"
                }
            },
            "columnDimensionSeparator": {
                "comment": {
                    "tags": {},
                    "shortText": "一意の列フィールド値を生成するときに使用されるセパレーター。"
                }
            },
            "rowDimensionSeparator": {
                "comment": {
                    "tags": {},
                    "shortText": "一意の行フィールド値を生成するときに使用されるセパレーター。"
                }
            }
        },
        "methods": {}
    }
}