{
    "IgxGridEditingActionsComponent": {
        "properties": {
            "editRow": {
                "comment": {
                    "blockTags": [],
                    "modifierTags": {},
                    "summary": [
                        {
                            "kind": "text",
                            "text": "An input to enable/disable action strip row editing button"
                        }
                    ]
                }
            },
            "deleteRow": {
                "comment": {
                    "blockTags": [],
                    "modifierTags": {},
                    "summary": [
                        {
                            "kind": "text",
                            "text": "An input to enable/disable action strip row deleting button"
                        }
                    ]
                }
            },
            "addChild": {
                "comment": {
                    "blockTags": [],
                    "modifierTags": {},
                    "summary": [
                        {
                            "kind": "text",
                            "text": "An input to enable/disable action strip child row adding button"
                        }
                    ]
                }
            },
            "asMenuItems": {
                "comment": {
                    "blockTags": [
                        {
                            "tag": "@example",
                            "content": [
                                {
                                    "kind": "code",
                                    "text": "```html\n <igx-grid-pinning-actions [asMenuItems]='true'></igx-grid-pinning-actions>\n <igx-grid-editing-actions [asMenuItems]='true'></igx-grid-editing-actions>\n```"
                                }
                            ]
                        }
                    ],
                    "modifierTags": {},
                    "summary": [
                        {
                            "kind": "text",
                            "text": "Gets/Sets if the action buttons will be rendered as menu items. When in menu, items will be rendered with text label."
                        }
                    ]
                }
            }
        },
        "methods": {
            "startEdit": {
                "comment": {
                    "blockTags": [
                        {
                            "tag": "@example",
                            "content": [
                                {
                                    "kind": "code",
                                    "text": "```typescript\nthis.gridEditingActions.startEdit();\n```"
                                }
                            ]
                        }
                    ],
                    "modifierTags": {},
                    "summary": [
                        {
                            "kind": "text",
                            "text": "Enter row or cell edit mode depending the grid rowEditable option"
                        }
                    ]
                }
            }
        },
        "accessors": {
            "addRow": {
                "setter": {
                    "comment": {
                        "blockTags": [],
                        "modifierTags": {},
                        "summary": [
                            {
                                "kind": "text",
                                "text": "An input to enable/disable action strip row adding button"
                            }
                        ]
                    }
                }
            }
        }
    }
}