{
    "IgxTabsComponent": {
        "properties": {
            "groups": {
                "comment": {
                    "shortText": [
                        "すべての `IgxTabsGroupComponent` の監視可能コレクションを提供します。",
                        "```typescript",
                        "const groupItems = this.myTabComponent.groups;",
                        "```"
                    ]
                }
            },
            "contentTabs": {
                "comment": {
                    "shortText": [
                        "ページで定義されているすべての `IgxTabItemComponent` の監視可能なコレクションを提供します。",
                        "```typescript",
                        "const tabItems = this.myTabComponent.contentTabs;",
                        "```"
                    ]
                }
            },
            "tabsType": {
                "comment": {
                    "shortText": [
                        "タブ ヘッダーのサイズ設定モードを定義します。`contentfit` または `fixed` に設定できます。",
                        "デフォルトのヘッダーのサイズ設定モードは `contentfit` です。",
                        "```html",
                        "<igx-tabs tabsType=\"fixed\">",
                        "    <igx-tabs-group label=\"HOME\">Home</igx-tabs-group>",
                        "</igx-tabs>",
                        "```"
                    ]
                }
            },
            "id": {
                "comment": {
                    "tags": {
                        "remarks": {
                            "comment": {
                                "text": "設定しない場合、`id` は `\"igx-tabs-0\"` 値を持ちます。",
                                "tagName": "備考"
                            }
                        },
                        "example": {
                            "comment": {
                                "text": [
                                    "```html",
                                    "<igx-tabs id=\"my-first-tabs\"></igx-tabs>",
                                    "```"
                                ],
                                "tagName": "例"
                            }
                        },
                        "memberof": {
                            "comment": {
                                "text": "IgxTabsComponent",
                                "tagName": "次のメンバー:"
                            }
                        }
                    },
                    "shortText": "タブの id を設定または取得します。"
                }
            },
            "onTabItemDeselected": {
                "comment": {
                    "shortText": [
                        "タブ項目が選択解除された時に発生されます。",
                        "```html",
                        "<igx-tabs (onTabItemDeselected)=\"itemDeselected($event)\">",
                        "     <igx-tabs-group label=\"Tab 1\">This is Tab 1 content.</igx-tabs-group>",
                        "     <igx-tabs-group label=\"Tab 2\">This is Tab 2 content.</igx-tabs-group>",
                        "</igx-tabs>",
                        "```",
                        "```typescript",
                        "itemDeselected(e){",
                        "     const tabGroup = e.group;",
                        "     const tabItem = e.tab;",
                        "}",
                        "```"
                    ]
                }
            },
            "onTabItemSelected": {
                "comment": {
                    "shortText": [
                        "タブ項目が選択された時に発生されます。",
                        "```html",
                        "<igx-tabs (onTabItemSelected)=\"itemSelected($event)\">",
                        "     <igx-tabs-group label=\"Tab 1\">This is Tab 1 content.</igx-tabs-group>",
                        "     <igx-tabs-group label=\"Tab 2\">This is Tab 2 content.</igx-tabs-group>",
                        "</igx-tabs>",
                        "```",
                        "```typescript",
                        "itemSelected(e){",
                        "     const tabGroup = e.group;",
                        "     const tabItem = e.tab;",
                        "}",
                        "```"
                    ]
                }
            },
            "viewTabs": {
                "comment": {
                    "shortText": [
                        "すべての `IgxTabItemComponent` の監視可能コレクションを提供します。",
                        "```typescript",
                        "const tabItems = this.myTabComponent.viewTabs;",
                        "```"
                    ]
                }
            }
        },
        "methods": {},
        "accessors": {
            "selectedIndex": {
                "getter": {
                    "comment": {
                        "text": [
                            "双方向データ バインディング。",
                            "```html",
                            "<igx-tabs [(selectedIndex)]=\"model.selectedIndex\">",
                            "```"
                        ],
                        "shortText": [
                            "`selectedIndex` の値を設定する @Input プロパティ。",
                            "デフォルト値は 0 です。",
                            "```html",
                            "<igx-tabs selectedIndex=\"1\">",
                            "```"
                        ]
                    }
                },
                "setter": {
                    "comment": {
                        "text": [
                            "双方向データ バインディング。",
                            "```html",
                            "<igx-tabs [(selectedIndex)]=\"model.selectedIndex\">",
                            "```"
                        ],
                        "shortText": [
                            "`selectedIndex` の値を設定する @Input プロパティ。",
                            "デフォルト値は 0 です。",
                            "```html",
                            "<igx-tabs selectedIndex=\"1\">",
                            "```"
                        ]
                    }
                }
            },
            "tabs": {
                "getter": {
                    "comment": {
                        "shortText": [
                            "すべての `IgxTabItemComponent` の監視可能コレクションを提供します。",
                            "最初にコンテンツの子として取得します。使用できない場合は、ビューの子として取得します。",
                            "```typescript",
                            "const tabItems = this.myTabComponent.tabs;",
                            "```"
                        ]
                    }
                }
            },
            "selectedTabItem": {
                "getter": {
                    "comment": {
                        "shortText": [
                            "選択された `IgxTabItemComponent` を取得します。",
                            "```",
                            "const selectedItem = this.myTabComponent.selectedTabItem;",
                            "```"
                        ]
                    }
                }
            }
        }
    }
}
