{
    "IgxBottomNavComponent": {
        "comment": {
            "tags": {
                "igxmodule": {
                    "comment": {
                        "text": "IgxBottomNavModule",
                        "tagName": "igxmodule"
                    }
                },
                "igxtheme": {
                    "comment": {
                        "text": "igx-bottom-nav-theme",
                        "tagName": "igxtheme"
                    }
                },
                "igxkeywords": {
                    "comment": {
                        "text": "bottom navigation",
                        "tagName": "igxkeywords"
                    }
                },
                "igxgroup": {
                    "comment": {
                        "text": "Layouts",
                        "tagName": "igxgroup"
                    }
                },
                "remarks": {
                    "comment": {
                        "tags": {},
                        "text": [
                            "Ignite UI for Angular Bottom Navigation コンポーネントを使用すると、単一のビューに表示される複数のコンテンツ間を移動できます。",
                            "コンテンツ間のナビゲーションは、下部にあるタブ ボタンで実行されます。"
                        ],
                        "tagName": "備考:"
                    }
                },
                "example": {
                    "comment": {
                        "tags": {},
                        "text": [
                            "```html",
                            "<igx-bottom-nav>",
                            "    <igx-bottom-nav-item>",
                            "        <igx-bottom-nav-header>",
                            "            <igx-icon igxBottomNavHeaderIcon>folder</igx-icon>",
                            "            <span igxBottomNavHeaderLabel>Tab 1</span>",
                            "        </igx-bottom-nav-header>",
                            "        <igx-bottom-nav-content>",
                            "            Content 1",
                            "        </igx-bottom-nav-content>",
                            "    </igx-bottom-nav-item>",
                            "    ...",
                            "</igx-bottom-nav>",
                            "```"
                        ],
                        "tagName": "例:"
                    }
                }
            },
            "shortText": "Bottom Navigation コンポーネントを使用すると、単一のビューに表示される複数のコンテンツ間を移動できます。"
        },
        "properties": {
            "selectedIndexChange": {
                "comment": {
                    "tags": {},
                    "shortText": "[(selectedIndex)] で双方向バインディングのサポートを有効にする出力。"
                }
            },
            "selectedIndexChanging": {
                "comment": {
                    "tags": {},
                    "shortText": "選択したインデックスが変更されようとしているときに発生されます。"
                }
            },
            "selectedItemChange": {
                "comment": {
                    "tags": {},
                    "shortText": "選択された項目が変更されたときに発生されます。"
                }
            },
            "items": {
                "comment": {
                    "tags": {},
                    "shortText": "項目を返します。"
                }
            }
        },
        "methods": {},
        "accessors": {
            "selectedIndex": {
                "getter": {
                    "comment": {
                        "tags": {},
                        "shortText": [
                            "選択された項目のインデックスを取得または設定する @Input プロパティ。",
                            "コンテンツが定義されている場合、デフォルト値は 0 です。それ以外の場合、デフォルトは  -1 です。"
                        ]
                    }
                },
                "setter": {
                    "comment": {
                        "tags": {},
                        "shortText": [
                            "選択された項目のインデックスを取得または設定する @Input プロパティ。",
                            "コンテンツが定義されている場合、デフォルト値は 0 です。それ以外の場合、デフォルトは  -1 です。"
                        ]
                    }
                }
            },
            "disableAnimation": {
                "getter": {
                    "comment": {
                        "tags": {},
                        "shortText": "コンテンツのトランジション アニメーションを有効または無効にします。"
                    }
                },
                "setter": {
                    "comment": {
                        "tags": {},
                        "shortText": "コンテンツのトランジション アニメーションを有効または無効にします。"
                    }
                }
            },
            "selectedItem": {
                "getter": {
                    "comment": {
                        "tags": {},
                        "shortText": "選択項目を取得します。"
                    }
                }
            }
        }
    }
}