{
    "IPinColumnEventArgs": {
        "comment": {
            "tags": {},
            "shortText": [
                "列のピン状態が変更された後のイベント引数。",
                "`insertAtIndex` は、列が挿入されたピン固定/ピン固定解除領域のどの位置に挿入されたかを指定します。",
                "`isPinned` は、操作が完了した後の列の実際のピン状態を返します。"
            ]
        },
        "properties": {
            "insertAtIndex": {
                "comment": {
                    "tags": {},
                    "shortText": [
                        "ピン固定されている場合は、ピン固定された領域のどのインデックスに列を挿入するかを指定します。",
                        "ピン固定されていない場合、列がピン固定されていない領域のどの位置に挿入されるかを指定します。"
                    ]
                }
            },
            "isPinned": {
                "comment": {
                    "tags": {},
                    "shortText": [
                        "列の実際のピン状態を返します。",
                        "ピン固定/ピン固定解除が成功すると、\"-ing\" および \"-ed\" イベントで読み取られたときに、それに応じて `isPinned` の値が変更されます。"
                    ]
                }
            },
            "owner": {
                "comment": {
                    "tags": {},
                    "shortText": "オーナー コンポーネントへの参照を提供します。"
                }
            }
        },
        "methods": {}
    }
}