{
    "/// @prop": {
        "description": [
            "<p>Light input-group スキーマを生成します。</p>",
            ""
        ]
    },
    "/// @property": {
        "description": [
            "<p>Light grid-toolbar スキーマを生成します。</p>",
            ""
        ]
    },
    "/// @see $default-palette\n$_light-slider: extend(\n    $_default-shape-slider,\n    (\n        variant: 'material',\n\n        tick-color:  (\n            igx-color: ('grays', 500)\n        ),\n\n        tick-color-tall:  (\n            igx-color: ('grays', 500)\n        ),\n\n        tick-label-color:  (\n            igx-color: ('grays', 500)\n        ),\n\n        tick-label-color-tall:  (\n            igx-color: ('grays', 900)\n        ),\n\n        track-color: (\n            igx-color: ('secondary', 500)\n        ),\n\n        thumb-color: (\n            igx-color: ('secondary', 500)\n        ),\n\n        thumb-border-color: (\n            igx-color: ('secondary', 500)\n        ),\n\n        label-background-color: (\n            igx-color: ('secondary', 500),\n            hexrgba: ()\n        ),\n\n        label-text-color: (\n            igx-contrast-color: ('secondary', 500)\n        ),\n\n        disabled-thumb-color: (\n            igx-color: ('grays', 400),\n            hexrgba: ()\n        ),\n\n        disabled-base-track-color: (\n            igx-color: ('grays', 400)\n        ),\n\n        thumb-disabled-border-color: (\n            igx-color: ('grays', 400)\n        ),\n\n        base-track-color: (\n            igx-color: ('secondary', 500),\n            rgba: .24\n        ),\n\n        base-track-hover-color:  (\n            igx-color: ('secondary', 500),\n            rgba: .24\n        ),\n\n        track-hover-color: (\n            igx-color: ('secondary', 500)\n        )\n    )\n);\n\n/// Generates a fluent slider schema.\n/// @type": {
        "description": [
            "<p>light slider スキーマを生成します。</p>",
            ""
        ]
    }
}