{
    "IListItemClickEventArgs": {
        "comment": {
            "blockTags": [],
            "modifierTags": {},
            "summary": [
                {
                    "kind": "text",
                    "text": "Interface for the listItemClick igxList event arguments"
                }
            ]
        },
        "properties": {
            "owner": {
                "comment": {
                    "blockTags": [],
                    "modifierTags": {},
                    "summary": [
                        {
                            "kind": "text",
                            "text": "Provides reference to the owner component."
                        }
                    ]
                }
            }
        },
        "methods": {}
    }
}