{
    "IgxMonthPickerBaseDirective": {
        "properties": {
            "activeViewIdx": {
                "comment": {
                    "tags": {},
                    "shortText": "操作する月ビューインデックスを保持します。"
                }
            },
            "hideOutsideDays": {
                "comment": {
                    "tags": {},
                    "shortText": [
                        "現在の月以外の日付を非表示にするかどうかを設定または取得します。",
                        "デフォルト値は `false` です。",
                        "```html",
                        "<igx-calendar [hideOutsideDays] = \"true\"></igx-calendar>",
                        "```",
                        "```typescript",
                        "let hideOutsideDays = this.calendar.hideOutsideDays;",
                        "```"
                    ]
                }
            },
            "selected": {
                "comment": {
                    "tags": {},
                    "shortText": [
                        "日付が選択されたときにイベントを発生します。",
                        "`selectedDates` プロパティに参照を提供します。"
                    ]
                }
            },
            "viewDateChanged": {
                "comment": {
                    "tags": {},
                    "shortText": [
                        "月ビューが変更されるときにイベントを発生します。",
                        "```html",
                        "<igx-calendar (viewDateChanged)=\"viewDateChanged($event)\"></igx-calendar>",
                        "```",
                        "```typescript",
                        "public viewDateChanged(event: IViewDateChangeEventArgs) {",
                        " let viewDate = event.currentValue;",
                        "}",
                        "```"
                    ]
                }
            },
            "activeViewChanged": {
                "comment": {
                    "tags": {},
                    "shortText": [
                        "アクティブ ビューが変更されるときにイベントを発生します。",
                        "```html",
                        "<igx-calendar (activeViewChanged)=\"activeViewChanged($event)\"></igx-calendar>",
                        "```",
                        "```typescript",
                        "public activeViewChanged(event: CalendarView) {",
                        " let activeView = event;",
                        "}",
                        "```"
                    ]
                }
            }
        },
        "methods": {
            "selectDate": {
                "comment": {
                    "tags": {},
                    "shortText": "日付を選択タイプに基づいて選択します。"
                }
            },
            "deselectDate": {
                "comment": {
                    "tags": {},
                    "shortText": "日付を選択タイプに基づいて選択解除します。"
                }
            }
        },
        "accessors": {
            "activeView": {
                "getter": {
                    "comment": {
                        "tags": {},
                        "shortText": [
                            "現在のアクティブ ビューを取得します。",
                            "```typescript",
                            "this.activeView = calendar.activeView;",
                            "```"
                        ]
                    }
                },
                "setter": {
                    "comment": {
                        "tags": {},
                        "shortText": [
                            "現在のアクティブ ビューを設定します。",
                            "```html",
                            "<igx-calendar [activeView]=\"year\" #calendar></igx-calendar>",
                            "```",
                            "```typescript",
                            "calendar.activeView = IgxCalendarView.YEAR;",
                            "```"
                        ]
                    }
                }
            },
            "resourceStrings": {
                "getter": {
                    "comment": {
                        "tags": {},
                        "shortText": "リソース文字列を返すアクセサー。"
                    }
                },
                "setter": {
                    "comment": {
                        "tags": {},
                        "shortText": [
                            "リソース文字列を設定するアクセサー。",
                            "デフォルトで EN リソースを使用します。"
                        ]
                    }
                }
            },
            "weekStart": {
                "getter": {
                    "comment": {
                        "tags": {},
                        "shortText": [
                            "週の最初の曜日を取得します。",
                            "曜日の数値または列挙型の表現を返します。",
                            "初期値は `Sunday` / `0` です。"
                        ]
                    }
                },
                "setter": {
                    "comment": {
                        "tags": {},
                        "shortText": [
                            "週の最初の曜日を設定します。",
                            "数値または `WEEKDAYS` の列挙型の値に割り当てます。"
                        ]
                    }
                }
            },
            "locale": {
                "getter": {
                    "comment": {
                        "tags": {},
                        "shortText": [
                            "カレンダーの `locale` を取得します。",
                            "デフォルト値は `\"en\"` です。"
                        ]
                    }
                },
                "setter": {
                    "comment": {
                        "tags": {},
                        "shortText": [
                            "カレンダーの `locale` を設定します。",
                            "有効な BCP 47 言語タグに設定します。",
                            "デフォルト値は `\"en\"` です。"
                        ]
                    }
                }
            },
            "formatOptions": {
                "getter": {
                    "comment": {
                        "tags": {},
                        "shortText": "日ビューの日付書式設定オプションを取得します。"
                    }
                },
                "setter": {
                    "comment": {
                        "tags": {},
                        "shortText": [
                            "日ビューの日付書式設定オプションを設定します。",
                            "デフォルト値は { day: 'numeric', month: 'short', weekday: 'short', year: 'numeric' } です。"
                        ]
                    }
                }
            },
            "formatViews": {
                "getter": {
                    "comment": {
                        "tags": {},
                        "shortText": [
                            "`day`、`month`、および `year` が `locale` および `formatOptions` によって描画されるかどうかを取得します。"
                        ]
                    }
                },
                "setter": {
                    "comment": {
                        "tags": {},
                        "shortText": [
                            "`day`、`month`、および `year` が `locale` および `formatOptions` によって描画されるかどうかを設定します。"
                        ]
                    }
                }
            },
            "selection": {
                "getter": {
                    "comment": {
                        "tags": {},
                        "shortText": [
                            "選択タイプを取得します。",
                            "デフォルト値は `\"single\"` です。",
                            "選択タイプを変更すると、現在選択されている値がリセットされます。"
                        ]
                    }
                },
                "setter": {
                    "comment": {
                        "tags": {},
                        "shortText": "選択を設定します。"
                    }
                }
            },
            "value": {
                "getter": {
                    "comment": {
                        "tags": {},
                        "text": [
                            "選択が `single` を設定した場合、単一の `Date` オブジェクトを返します。",
                            "それ以外の場合、`Date` オブジェクトの配列です。"
                        ],
                        "shortText": "選択された日付を設定します。"
                    }
                },
                "setter": {
                    "comment": {
                        "tags": {},
                        "text": [
                            "選択が `single` に設定される場合、単一の `Date` オブジェクトを許容します。",
                            "それ以外の場合、`Date` オブジェクトの配列です。"
                        ],
                        "shortText": "選択された日付を設定します。"
                    }
                }
            },
            "viewDate": {
                "getter": {
                    "comment": {
                        "tags": {},
                        "shortText": [
                            "表示される日付を取得します。",
                            "デフォルト値は現在の日付です。"
                        ]
                    }
                },
                "setter": {
                    "comment": {
                        "tags": {},
                        "shortText": "コンポーネントを描画するときにデフォルト ビューで表示される日付を設定します。"
                    }
                }
            },
            "disabledDates": {
                "getter": {
                    "comment": {
                        "tags": {},
                        "shortText": "無効な日付記述子を取得します。"
                    }
                },
                "setter": {
                    "comment": {
                        "tags": {},
                        "shortText": [
                            "無効な日付記述子を設定します。",
                            "```typescript",
                            "@ViewChild(\"MyCalendar\")",
                            "public calendar: IgxCalendarComponent;",
                            "ngOnInit(){",
                            "   this.calendar.disabledDates = [",
                            "    {type: DateRangeType.Between, dateRange: [new Date(\"2020-1-1\"), new Date(\"2020-1-15\")]},",
                            "    {type: DateRangeType.Weekends}];",
                            "}",
                            "```"
                        ]
                    }
                }
            },
            "specialDates": {
                "getter": {
                    "comment": {
                        "tags": {},
                        "shortText": "特別な日付記述子を取得します。"
                    }
                },
                "setter": {
                    "comment": {
                        "tags": {},
                        "shortText": [
                            "特別な日付記述子を設定します。",
                            "```typescript",
                            "@ViewChild(\"MyCalendar\")",
                            "public calendar: IgxCalendarComponent;",
                            "ngOnInit(){",
                            "   this.calendar.specialDates = [",
                            "    {type: DateRangeType.Between, dateRange: [new Date(\"2020-1-1\"), new Date(\"2020-1-15\")]},",
                            "    {type: DateRangeType.Weekends}];",
                            "}",
                            "```"
                        ]
                    }
                }
            }
        }
    }
}